{
    "key": "group_675a4e7d8f9a2",
    "title": "Блок: Послуги",
    "fields": [
        {
            "key": "field_675a4e7d8f9a3",
            "label": "Контент",
            "name": "",
            "aria-label": "",
            "type": "accordion",
            "instructions": "",
            "required": 0,
            "conditional_logic": 0,
            "wrapper": {
                "width": "",
                "class": "",
                "id": ""
            },
            "wpml_cf_preferences": 1,
            "open": 0,
            "multi_expand": 0,
            "endpoint": 0
        },
        {
            "key": "field_68f42ddd4683c",
            "label": "Послуги",
            "name": "services",
            "aria-label": "",
            "type": "relationship",
            "instructions": "",
            "required": 0,
            "conditional_logic": 0,
            "wrapper": {
                "width": "",
                "class": "",
                "id": ""
            },
            "wpml_cf_preferences": 1,
            "post_type": [
                "page"
            ],
            "post_status": [
                "publish"
            ],
            "taxonomy": "",
            "filters": "",
            "return_format": "id",
            "min": "",
            "max": "",
            "allow_in_bindings": 0,
            "elements": [
                "featured_image"
            ],
            "bidirectional": 0,
            "bidirectional_target": []
        }
    ],
    "location": [
        [
            {
                "param": "block",
                "operator": "==",
                "value": "acf\/main-services"
            }
        ]
    ],
    "menu_order": 103,
    "position": "normal",
    "style": "default",
    "label_placement": "top",
    "instruction_placement": "label",
    "hide_on_screen": "",
    "active": true,
    "description": "",
    "show_in_rest": 0,
    "display_title": "",
    "acfml_field_group_mode": "translation",
    "modified": 1760968022
}
